arrendatools_modelo_303/__init__.py
arrendatools_modelo_303/modelo_303.py
arrendatools_modelo_303/periodos.py
arrendatools_modelo_303-2023.0.3.dist-info/LICENSE
arrendatools_modelo_303-2023.0.3.dist-info/METADATA
arrendatools_modelo_303-2023.0.3.dist-info/WHEEL
arrendatools_modelo_303-2023.0.3.dist-info/top_level.txt
arrendatools_modelo_303-2023.0.3.dist-info/RECORD
