Metadata-Version: 2.1
Name: arrendatools-modelo-303
Version: 2023.0.3
Summary: Módulo de Python que genera un string para la importación de datos en el modelo 303 de la Agencia Tributaria de España (PRE 303 - Servicio ayuda modelo 303)
Home-page: https://github.com/hokus15/ArrendaToolsModelo303
Author: hokus15
Author-email: hokus@hotmail.com
License: MIT
Classifier: Development Status :: 4 - Beta
Classifier: Intended Audience :: Developers
Classifier: License :: OSI Approved :: MIT License
Classifier: Programming Language :: Python :: 3.7
Classifier: Programming Language :: Python :: 3.8
Classifier: Programming Language :: Python :: 3.9
Classifier: Programming Language :: Python :: 3.10
Classifier: Programming Language :: Python :: 3.11
License-File: LICENSE
